Scripts/Spotify.py
Scripts/__init__.py
Spotify_recommendation_ptp-0.1.8.dist-info/METADATA
Spotify_recommendation_ptp-0.1.8.dist-info/WHEEL
Spotify_recommendation_ptp-0.1.8.dist-info/top_level.txt
Spotify_recommendation_ptp-0.1.8.dist-info/RECORD
